odoo/addons/hr_attendance_sheet/README.rst
odoo/addons/hr_attendance_sheet/__init__.py
odoo/addons/hr_attendance_sheet/__manifest__.py
odoo/addons/hr_attendance_sheet/data/cron.xml
odoo/addons/hr_attendance_sheet/data/mail_data.xml
odoo/addons/hr_attendance_sheet/i18n/hr_attendance_sheet.pot
odoo/addons/hr_attendance_sheet/i18n/it.po
odoo/addons/hr_attendance_sheet/i18n/pt_BR.po
odoo/addons/hr_attendance_sheet/models/__init__.py
odoo/addons/hr_attendance_sheet/models/hr_attendance.py
odoo/addons/hr_attendance_sheet/models/hr_attendance_sheet.py
odoo/addons/hr_attendance_sheet/models/hr_department.py
odoo/addons/hr_attendance_sheet/models/hr_employee.py
odoo/addons/hr_attendance_sheet/models/res_company.py
odoo/addons/hr_attendance_sheet/models/res_config.py
odoo/addons/hr_attendance_sheet/readme/CONFIGURE.rst
odoo/addons/hr_attendance_sheet/readme/CONTRIBUTORS.rst
odoo/addons/hr_attendance_sheet/readme/DESCRIPTION.rst
odoo/addons/hr_attendance_sheet/readme/USAGE.rst
odoo/addons/hr_attendance_sheet/report/hr_attendance_sheet_report.xml
odoo/addons/hr_attendance_sheet/security/ir.model.access.csv
odoo/addons/hr_attendance_sheet/security/security_groups.xml
odoo/addons/hr_attendance_sheet/static/description/icon.png
odoo/addons/hr_attendance_sheet/static/description/index.html
odoo/addons/hr_attendance_sheet/tests/__init__.py
odoo/addons/hr_attendance_sheet/tests/test_attendance_sheet.py
odoo/addons/hr_attendance_sheet/views/hr_attendance_sheet.xml
odoo/addons/hr_attendance_sheet/views/hr_attendance_view.xml
odoo/addons/hr_attendance_sheet/views/hr_department.xml
odoo/addons/hr_attendance_sheet/views/hr_employee.xml
odoo/addons/hr_attendance_sheet/views/res_company.xml
odoo/addons/hr_attendance_sheet/views/res_config_settings_views.xml
odoo12_addon_hr_attendance_sheet-12.0.1.0.0.99.dev13.dist-info/METADATA
odoo12_addon_hr_attendance_sheet-12.0.1.0.0.99.dev13.dist-info/WHEEL
odoo12_addon_hr_attendance_sheet-12.0.1.0.0.99.dev13.dist-info/top_level.txt
odoo12_addon_hr_attendance_sheet-12.0.1.0.0.99.dev13.dist-info/RECORD
